pdec/__init__.py
pdec/_modidx.py
pdec/_tmp.py
pdec/core.py
pdec-0.0.4.dist-info/LICENSE
pdec-0.0.4.dist-info/METADATA
pdec-0.0.4.dist-info/WHEEL
pdec-0.0.4.dist-info/entry_points.txt
pdec-0.0.4.dist-info/top_level.txt
pdec-0.0.4.dist-info/RECORD
