Metadata-Version: 2.1
Name: pdec
Version: 0.0.4
Summary: pdec (prototype)
Home-page: https://github.com/dsm-72/pdec
Author: dsm-72
Author-email: sumner.magruder@yale.edu
License: Apache Software License 2.0
Keywords: property prop slot props slots properties decorator pdec deco
Classifier: Development Status :: 4 - Beta
Classifier: Intended Audience :: Developers
Classifier: Natural Language :: English
Classifier: Programming Language :: Python :: 3.11
Classifier: License :: OSI Approved :: Apache Software License
Requires-Python: >=3.11
License-File: LICENSE
Requires-Dist: nchr
Requires-Dist: nlit
Provides-Extra: dev
